MANIFEST.in
README.md
license.txt
setup.py
PyOpenFDM.egg-info/PKG-INFO
PyOpenFDM.egg-info/SOURCES.txt
PyOpenFDM.egg-info/dependency_links.txt
PyOpenFDM.egg-info/entry_points.txt
PyOpenFDM.egg-info/requires.txt
PyOpenFDM.egg-info/top_level.txt
pyopenfdm/__init__.py
pyopenfdm/deps.py
pyopenfdm/plot.py
pyopenfdm/run.py
pyopenfdm/deps/DyMat/DyMat/__init__.py
pyopenfdm/deps/DyMat/DyMat/Export/CSV.py
pyopenfdm/deps/DyMat/DyMat/Export/CSVlocale.py
pyopenfdm/deps/DyMat/DyMat/Export/Gnuplot.py
pyopenfdm/deps/DyMat/DyMat/Export/MATLAB.py
pyopenfdm/deps/DyMat/DyMat/Export/__init__.py
pyopenfdm/deps/DyMat/DyMat/Export/netCDF.py
pyopenfdm/deps/DyMat/DyMat/Plot/__init__.py
pyopenfdm/deps/OMPython/OMPython/OMConfig.py
pyopenfdm/deps/OMPython/OMPython/__init__.py
pyopenfdm/deps/OMPython/OMPython/OMParser/__init__.py
pyopenfdm/deps/OMPython/OMPythonIDL/__init__.py
pyopenfdm/deps/OMPython/OMPythonIDL/omc_communication_idl.py
pyopenfdm/deps/OMPython/OMPythonIDL/_OMCIDL/__init__.py
pyopenfdm/deps/OMPython/OMPythonIDL/_OMCIDL__POA/__init__.py
test/test.py