Metadata-Version: 1.1
Name: PyOpenFDM
Version: 0.0.1
Summary: A package for aerospace simulation in Modelica
Home-page: git@github.com:arktools/openfdm.git
Author: James Goppert
Author-email: james.goppert@gmail.com
License: GPLv3
Keywords: modelica dymola openmodelica mat fdm aerospace flight dynamic model
Platform: UNKNOWN
Classifier: Development Status :: 4 - Beta
Classifier: Environment :: Console
Classifier: Intended Audience :: Science/Research
Classifier: License :: OSI Approved :: GNU General Public License v3 (GPLv3)
Classifier: Operating System :: OS Independent
Classifier: Programming Language :: Python :: 2.7
Classifier: Topic :: Scientific/Engineering
